MANIFEST.in
README.md
setup.cfg
setup.py
pyrhessys/__init__.py
pyrhessys/ensemble.py
pyrhessys/evaluation.py
pyrhessys/input_configure.py
pyrhessys/ostrich.py
pyrhessys/plotting.py
pyrhessys/read_meta.py
pyrhessys/read_rcode.py
pyrhessys/read_shellscript.py
pyrhessys/read_template.py
pyrhessys/rhessys_simulation.py
pyrhessys/simulation.py
pyrhessys/utils.py
pyrhessys.egg-info/PKG-INFO
pyrhessys.egg-info/SOURCES.txt
pyrhessys.egg-info/dependency_links.txt
pyrhessys.egg-info/requires.txt
pyrhessys.egg-info/top_level.txt
pyrhessys/meta/file_name.json
pyrhessys/meta/hillCollection.csv
pyrhessys/meta/lulcCollection.csv
pyrhessys/meta/lulcCollectionEC.csv
pyrhessys/meta/lulc_difficult_run_fraction.csv
pyrhessys/meta/lulc_forest_fraction.csv
pyrhessys/meta/lulc_meadow_creek_fraction.csv
pyrhessys/meta/lulc_urban_fraction.csv
pyrhessys/meta/output_variables.json
pyrhessys/meta/parameter_meta.json
pyrhessys/meta/soilCollection.csv
pyrhessys/meta/vegCollection.csv
pyrhessys/meta/zoneCollection.csv
pyrhessys/r_code/LIB_RHESSys_readWorld2Table.R
pyrhessys/r_code/LIB_RHESSys_writeTable2World.R
pyrhessys/r_code/LIB_misc.R
pyrhessys/r_code/aggregate_vegFfrac_write2GIS.R
pyrhessys/r_code/aggregate_vegLAI_write2GIS.R
pyrhessys/r_code/basin_extraction.R
pyrhessys/r_code/createFlowRouting.R
pyrhessys/r_code/elevation_analysis.R
pyrhessys/r_code/g2w.R
pyrhessys/r_code/g2w_c.R
pyrhessys/r_code/g2w_cf_RHESSysEC.R
pyrhessys/r_code/g2world.R
pyrhessys/r_code/g2world_def_flow.R
pyrhessys/r_code/lai_codeinformation.R
pyrhessys/r_code/linear_elevation_edit.R
pyrhessys/r_code/lulc2rhessys.R
pyrhessys/r_code/lulcFrac_write2gis.R
pyrhessys/r_code/lulc_codeinformation.R
pyrhessys/r_code/nlcd2rhessys.R
pyrhessys/r_code/patch_lulc_extraction.R
pyrhessys/r_code/road_storm_drainage_outlet.R
pyrhessys/r_code/ssurgo_extraction.R
pyrhessys/r_code/ssurgo_properties_extraction1.R
pyrhessys/r_code/ssurgo_properties_extraction2.R
pyrhessys/r_code/ssurgo_properties_extraction3.R
pyrhessys/r_code/ssurgo_soiltexture2gis.R
pyrhessys/r_code/veg_codeinformation.R
pyrhessys/r_code/well_septicdrainfield_Irrigrationlawn_around_rooftops.R
pyrhessys/r_code/zone_cluster.R
