Metadata-Version: 2.1
Name: pyrhessys
Version: 0.0.4
Summary: an Object-Oriented Python wrapper for the RHESSys model
Home-page: https://github.com/DavidChoi76/pyrhessys.git
Author: YoungDon Choi
Author-email: choiyd1115@gmail.com
License: MIT
Platform: UNKNOWN
Provides-Extra: visualization
